metapic.py
metapic-0.1.0.data/data/HISTORY.md
metapic-0.1.0.data/data/LICENSE
metapic-0.1.0.dist-info/LICENSE
metapic-0.1.0.dist-info/METADATA
metapic-0.1.0.dist-info/WHEEL
metapic-0.1.0.dist-info/entry_points.txt
metapic-0.1.0.dist-info/top_level.txt
metapic-0.1.0.dist-info/zip-safe
metapic-0.1.0.dist-info/RECORD
