Metadata-Version: 2.1
Name: metapic
Version: 0.1.0
Summary: Command line tool for modifying picture metadata from file/folder names and config.
Home-page: https://github.com/luphord/metapic
Author: luphord
Author-email: luphord@protonmail.com
License: MIT license
Keywords: metapic
Platform: UNKNOWN
Classifier: Development Status :: 2 - Pre-Alpha
Classifier: Intended Audience :: Developers
Classifier: License :: OSI Approved :: MIT License
Classifier: Natural Language :: English
Classifier: Programming Language :: Python :: 3
Classifier: Programming Language :: Python :: 3.6
Classifier: Programming Language :: Python :: 3.7
Classifier: Programming Language :: Python :: 3.8
Requires-Python: >=3.6
